setup.py
lansfer/__init__.py
lansfer/rf.py
lansfer/sf.py
lansfer/utils.py
lansfer.egg-info/PKG-INFO
lansfer.egg-info/SOURCES.txt
lansfer.egg-info/dependency_links.txt
lansfer.egg-info/entry_points.txt
lansfer.egg-info/requires.txt
lansfer.egg-info/top_level.txt