Metadata-Version: 1.0
Name: lansfer
Version: 0.1.5
Summary: A simple tool for transfer file in LAN
Home-page: xlvecle.github.io/lansfer
Author: xlvecle
Author-email: xingke0@gmail
License:             DO WHAT THE FUCK YOU WANT TO PUBLIC LICENSE
